.gitignore
.travis.yml
CHANGES.rst
LICENSE
MANIFEST.in
Makefile
README.rst
setup.cfg
setup.py
tox.ini
docs/.gitignore
docs/Makefile
docs/conf.py
docs/index.rst
senic/__init__.py
senic.cryptoyaml.egg-info/PKG-INFO
senic.cryptoyaml.egg-info/SOURCES.txt
senic.cryptoyaml.egg-info/dependency_links.txt
senic.cryptoyaml.egg-info/entry_points.txt
senic.cryptoyaml.egg-info/namespace_packages.txt
senic.cryptoyaml.egg-info/not-zip-safe
senic.cryptoyaml.egg-info/requires.txt
senic.cryptoyaml.egg-info/top_level.txt
senic/cryptoyaml/.coveragerc
senic/cryptoyaml/__init__.py
senic/cryptoyaml/api.py
senic/cryptoyaml/commands.py
senic/cryptoyaml/testing.py
senic/cryptoyaml/tests/.DS_Store
senic/cryptoyaml/tests/conftest.py
senic/cryptoyaml/tests/test_api.py
senic/cryptoyaml/tests/data/plaintext.yml
senic/cryptoyaml/tests/data/secret
senic/cryptoyaml/tests/data/settings.yml.aes