Metadata-Version: 1.1
Name: senic.cryptoyaml
Version: 0.1.1
Summary: A python library to manage encrypted YAML files.
Home-page: https://github.com/getsenic/senic.cryptoyaml
Author: Senic GmbH
Author-email: tom@senic.com
License: BSD 2-Clause License
Platform: UNKNOWN
Classifier: Programming Language :: Python
